pfc_toolkit-2024.2.15.1.data/scripts/connectome_precomputed
pfc_toolkit-2024.2.15.1.data/scripts/generate_pfc_combo_chunks
pfc_toolkit-2024.2.15.1.data/scripts/generate_pfc_fc_chunks
pfc_toolkit-2024.2.15.1.data/scripts/generate_pfc_weighted_masks
pfctoolkit/__init__.py
pfctoolkit/chunker.py
pfctoolkit/config.py
pfctoolkit/datasets.py
pfctoolkit/mapping.py
pfctoolkit/processing.py
pfctoolkit/surface.py
pfctoolkit/tools.py
pfctoolkit/configs/__init__.py
pfctoolkit/configs/discovery-yeo1000_dil.json
pfctoolkit/configs/helium-yeo1000_dil.json
pfctoolkit/data/MNI152_T1_1mm_brain.nii.gz
pfctoolkit/data/MNI152_T1_1mm_brain_mask.nii.gz
pfctoolkit/data/MNI152_T1_1mm_brain_mask_dil.nii.gz
pfctoolkit/data/MNI152_T1_2mm_brain.nii.gz
pfctoolkit/data/MNI152_T1_2mm_brain_mask.nii.gz
pfctoolkit/data/MNI152_T1_2mm_brain_mask_dil.nii.gz
pfctoolkit/data/__init__.py
pfctoolkit/data/fs5_mask.gii
pfctoolkit/data/fs5_mask_lh.gii
pfctoolkit/data/fs5_mask_rh.gii
pfctoolkit/scripts/connectome_precomputed
pfctoolkit/scripts/generate_pfc_combo_chunks
pfctoolkit/scripts/generate_pfc_fc_chunks
pfctoolkit/scripts/generate_pfc_weighted_masks
pfc_toolkit-2024.2.15.1.dist-info/LICENSE
pfc_toolkit-2024.2.15.1.dist-info/METADATA
pfc_toolkit-2024.2.15.1.dist-info/WHEEL
pfc_toolkit-2024.2.15.1.dist-info/top_level.txt
pfc_toolkit-2024.2.15.1.dist-info/RECORD
